FilMoreBlanks/__init__.py
FilMoreBlanks/blanket_fill.py
FilMoreBlanks-1.1.0.dist-info/LICENSE
FilMoreBlanks-1.1.0.dist-info/METADATA
FilMoreBlanks-1.1.0.dist-info/WHEEL
FilMoreBlanks-1.1.0.dist-info/top_level.txt
FilMoreBlanks-1.1.0.dist-info/RECORD
