Metadata-Version: 2.1
Name: FilMoreBlanks
Version: 1.1.0
Summary: CSV fill in the blank editor
Home-page: https://github.com/OObasuyi/FilMoreBlanks
Author: Osamuede Obasuyi
Author-email: pypi@blankmarks.com
Classifier: License :: OSI Approved :: MIT License
Classifier: Operating System :: OS Independent
Classifier: Programming Language :: Python :: 3
Classifier: Topic :: System :: Networking
Classifier: Topic :: System :: Networking :: Firewalls
Classifier: Topic :: Security
Classifier: Topic :: Text Processing
Requires-Python: >=3.8
License-File: LICENSE
